falconpy/README.md
falconpy/__init__.py
falconpy/_version.py
falconpy/alerts.py
falconpy/api_integrations.py
falconpy/aspm.py
falconpy/cao_hunting.py
falconpy/case_management.py
falconpy/certificate_based_exclusions.py
falconpy/cloud_aws_registration.py
falconpy/cloud_azure_registration.py
falconpy/cloud_connect_aws.py
falconpy/cloud_google_cloud_registration.py
falconpy/cloud_oci_registration.py
falconpy/cloud_policies.py
falconpy/cloud_security.py
falconpy/cloud_security_assets.py
falconpy/cloud_security_compliance.py
falconpy/cloud_security_detections.py
falconpy/cloud_snapshots.py
falconpy/configuration_assessment.py
falconpy/configuration_assessment_evaluation_logic.py
falconpy/container_alerts.py
falconpy/container_detections.py
falconpy/container_image_compliance.py
falconpy/container_images.py
falconpy/container_packages.py
falconpy/container_vulnerabilities.py
falconpy/content_update_policies.py
falconpy/correlation_rules.py
falconpy/correlation_rules_admin.py
falconpy/cspm_registration.py
falconpy/custom_ioa.py
falconpy/custom_storage.py
falconpy/d4c_registration.py
falconpy/data_protection_configuration.py
falconpy/debug.py
falconpy/delivery_settings.py
falconpy/deployments.py
falconpy/detects.py
falconpy/device_content.py
falconpy/device_control_policies.py
falconpy/discover.py
falconpy/downloads.py
falconpy/drift_indicators.py
falconpy/event_streams.py
falconpy/exposure_management.py
falconpy/faas_execution.py
falconpy/falcon_complete_dashboard.py
falconpy/falcon_container.py
falconpy/falconx_sandbox.py
falconpy/fdr.py
falconpy/filevantage.py
falconpy/firewall_management.py
falconpy/firewall_policies.py
falconpy/foundry_logscale.py
falconpy/host_group.py
falconpy/host_migration.py
falconpy/hosts.py
falconpy/identity_protection.py
falconpy/image_assessment_policies.py
falconpy/incidents.py
falconpy/installation_tokens.py
falconpy/intel.py
falconpy/intelligence_feeds.py
falconpy/intelligence_indicator_graph.py
falconpy/ioa_exclusions.py
falconpy/ioc.py
crowdstrike_falconpy-1.5.5.dist-info/METADATA
crowdstrike_falconpy-1.5.5.dist-info/WHEEL
crowdstrike_falconpy-1.5.5.dist-info/licenses/AUTHORS.md
crowdstrike_falconpy-1.5.5.dist-info/licenses/LICENSE
crowdstrike_falconpy-1.5.5.dist-info/RECORD
